{"2":{"1":[{"1":"goog.net.WebSocket.EventType","5":{"1":"closure/goog/net/websocket.js","2":157,"3":"https://github.com/google/closure-library/blob/master/closure/goog/net/websocket.js#L157"},"7":{"1":[{"2":"<p>The events fired by the web socket.</p>\n"}]},"8":{},"11":{"1":{"4":{"1":"string","3":{"1":"https://developer.mozilla.org/en-US/docs/Web/JavaScript/Reference/Global_Objects/String"},"4":true}},"2":[{"1":"CLOSED","2":{"1":[{"2":"<p>Fired when an attempt to open the WebSocket fails or there is a connection\nfailure after a successful connection has been established.</p>\n"}]}},{"1":"ERROR","2":{"1":[{"2":"<p>Fired when the WebSocket encounters an error.</p>\n"}]}},{"1":"MESSAGE","2":{"1":[{"2":"<p>Fired when a new message arrives from the WebSocket.</p>\n"}]}},{"1":"OPENED","2":{"1":[{"2":"<p>Fired when the WebSocket connection has been established.</p>\n"}]}}]},"21":{"1":{"1":"goog.net","3":{"1":"goog.net.html"}}},"23":"goog.net.WebSocket.EventType.html","24":"goog.net.WebSocket.EventType"}]}}