{"2":{"1":[{"1":"goog.ui.ac.ArrayMatcher","5":{"1":"closure/goog/ui/ac/arraymatcher.js","2":35,"3":"https://github.com/google/closure-library/blob/master/closure/goog/ui/ac/arraymatcher.js#L35"},"7":{"1":[{"2":"<p>Basic class for matching words in an array</p>\n"}]},"8":{},"12":[{"1":{"1":"ArrayMatcher.getMatchesForRows","2":{"1":"closure/goog/ui/ac/arraymatcher.js","2":78,"3":"https://github.com/google/closure-library/blob/master/closure/goog/ui/ac/arraymatcher.js#L78"},"3":{"1":[{"2":"<p>Matches the token against the specified rows, first looking for prefix\nmatches and if that fails, then looking for similar matches.</p>\n"}]}},"4":[{"1":"token","2":{"4":{"1":"string","4":true}},"3":{"1":[{"2":"<p>Token to match.</p>\n"}]}},{"1":"maxMatches","2":{"4":{"1":"number","4":true}},"3":{"1":[{"2":"<p>Max number of matches to return.</p>\n"}]}},{"1":"rows","2":{"4":{"1":"Array","4":true,"5":[{"8":true}]}},"3":{"1":[{"2":"<p>Rows to search for matches. Can be objects if they\nhave a toString method that returns the value to match against.</p>\n"}]}}],"5":{"2":{"4":{"1":"Array","4":true,"5":[{"8":true}]}},"3":{"1":[{"2":"<p>Rows that match.</p>\n"}]}}},{"1":{"1":"ArrayMatcher.getPrefixMatchesForRows","2":{"1":"closure/goog/ui/ac/arraymatcher.js","2":112,"3":"https://github.com/google/closure-library/blob/master/closure/goog/ui/ac/arraymatcher.js#L112"},"3":{"1":[{"2":"<p>Matches the token against the start of words in the row.</p>\n"}]}},"4":[{"1":"token","2":{"4":{"1":"string","4":true}},"3":{"1":[{"2":"<p>Token to match.</p>\n"}]}},{"1":"maxMatches","2":{"4":{"1":"number","4":true}},"3":{"1":[{"2":"<p>Max number of matches to return.</p>\n"}]}},{"1":"rows","2":{"4":{"1":"Array","4":true,"5":[{"8":true}]}},"3":{"1":[{"2":"<p>Rows to search for matches. Can be objects if they\nhave\na toString method that returns the value to match against.</p>\n"}]}}],"5":{"2":{"4":{"1":"Array","4":true,"5":[{"8":true}]}},"3":{"1":[{"2":"<p>Rows that match.</p>\n"}]}}},{"1":{"1":"ArrayMatcher.getSimilarMatchesForRows","2":{"1":"closure/goog/ui/ac/arraymatcher.js","2":154,"3":"https://github.com/google/closure-library/blob/master/closure/goog/ui/ac/arraymatcher.js#L154"},"3":{"1":[{"2":"<p>Matches the token against similar rows, by calculating &#34;distance&#34; between the\nterms.</p>\n"}]}},"4":[{"1":"token","2":{"4":{"1":"string","4":true}},"3":{"1":[{"2":"<p>Token to match.</p>\n"}]}},{"1":"maxMatches","2":{"4":{"1":"number","4":true}},"3":{"1":[{"2":"<p>Max number of matches to return.</p>\n"}]}},{"1":"rows","2":{"4":{"1":"Array","4":true,"5":[{"8":true}]}},"3":{"1":[{"2":"<p>Rows to search for matches. Can be objects\nif they have a toString method that returns the value to\nmatch against.</p>\n"}]}}],"5":{"2":{"4":{"1":"Array","4":true,"5":[{"8":true}]}},"3":{"1":[{"2":"<p>The best maxMatches rows.</p>\n"}]}}}],"14":{"1":{"1":"ArrayMatcher","2":{"1":"closure/goog/ui/ac/arraymatcher.js","2":35,"3":"https://github.com/google/closure-library/blob/master/closure/goog/ui/ac/arraymatcher.js#L35"},"3":{"1":[{"2":"<p>Basic class for matching words in an array</p>\n"}]}},"3":true,"4":[{"1":"rows","2":{"6":{"1":[{"4":{"1":"Array","4":true,"5":[{"8":true}]}},{"10":true}]}},"3":{"1":[{"2":"<p>Dictionary of items to match.  Can be objects if they\nhave a toString method that returns the value to match against.</p>\n"}]}},{"1":"opt_noSimilar","2":{"1":true,"6":{"1":[{"4":{"1":"boolean","4":true}},{"9":true}]}},"3":{"1":[{"2":"<p>if true, do not do similarity matches for the\ninput token against the dictionary.</p>\n"}]}}]},"15":[{"1":{"1":"getPrefixMatches","2":{"1":"closure/goog/ui/ac/arraymatcher.js","2":96,"3":"https://github.com/google/closure-library/blob/master/closure/goog/ui/ac/arraymatcher.js#L96"},"3":{"1":[{"2":"<p>Matches the token against the start of words in the row.</p>\n"}]}},"4":[{"1":"token","2":{"4":{"1":"string","4":true}},"3":{"1":[{"2":"<p>Token to match.</p>\n"}]}},{"1":"maxMatches","2":{"4":{"1":"number","4":true}},"3":{"1":[{"2":"<p>Max number of matches to return.</p>\n"}]}}],"5":{"2":{"4":{"1":"Array","4":true,"5":[{"8":true}]}},"3":{"1":[{"2":"<p>Rows that match.</p>\n"}]}}},{"1":{"1":"getSimilarRows","2":{"1":"closure/goog/ui/ac/arraymatcher.js","2":138,"3":"https://github.com/google/closure-library/blob/master/closure/goog/ui/ac/arraymatcher.js#L138"},"3":{"1":[{"2":"<p>Matches the token against similar rows, by calculating &#34;distance&#34; between the\nterms.</p>\n"}]}},"4":[{"1":"token","2":{"4":{"1":"string","4":true}},"3":{"1":[{"2":"<p>Token to match.</p>\n"}]}},{"1":"maxMatches","2":{"4":{"1":"number","4":true}},"3":{"1":[{"2":"<p>Max number of matches to return.</p>\n"}]}}],"5":{"2":{"4":{"1":"Array","4":true,"5":[{"8":true}]}},"3":{"1":[{"2":"<p>The best maxMatches rows.</p>\n"}]}}},{"1":{"1":"requestMatchingRows","2":{"1":"closure/goog/ui/ac/arraymatcher.js","2":57,"3":"https://github.com/google/closure-library/blob/master/closure/goog/ui/ac/arraymatcher.js#L57"},"3":{"1":[{"2":"<p>Function used to pass matches to the autocomplete</p>\n"}]}},"4":[{"1":"token","2":{"4":{"1":"string","4":true}},"3":{"1":[{"2":"<p>Token to match.</p>\n"}]}},{"1":"maxMatches","2":{"4":{"1":"number","4":true}},"3":{"1":[{"2":"<p>Max number of matches to return.</p>\n"}]}},{"1":"matchHandler","2":{"6":{"1":[{"4":{"1":"Function"}},{"10":true}]}},"3":{"1":[{"2":"<p>callback to execute after matching.</p>\n"}]}},{"1":"opt_fullString","2":{"1":true,"6":{"1":[{"4":{"1":"string","4":true}},{"9":true}]}},"3":{"1":[{"2":"<p>The full string from the input box.</p>\n"}]}}]},{"1":{"1":"setRows","2":{"1":"closure/goog/ui/ac/arraymatcher.js","2":45,"3":"https://github.com/google/closure-library/blob/master/closure/goog/ui/ac/arraymatcher.js#L45"},"3":{"1":[{"2":"<p>Replaces the rows that this object searches over.</p>\n"}]}},"4":[{"1":"rows","2":{"6":{"1":[{"4":{"1":"Array","4":true,"5":[{"8":true}]}},{"10":true}]}},"3":{"1":[{"2":"<p>Dictionary of items to match.</p>\n"}]}}]}],"16":[{"1":{"1":"rows_","2":{"1":"closure/goog/ui/ac/arraymatcher.js","2":46,"3":"https://github.com/google/closure-library/blob/master/closure/goog/ui/ac/arraymatcher.js#L46"},"3":{}},"2":{"4":{"1":"Array","4":true,"5":[{"8":true}]}}},{"1":{"1":"useSimilar_","2":{"1":"closure/goog/ui/ac/arraymatcher.js","2":37,"3":"https://github.com/google/closure-library/blob/master/closure/goog/ui/ac/arraymatcher.js#L37"},"3":{}},"2":{"4":{"1":"boolean","4":true}}}],"21":{"1":{"1":"goog.ui.ac.ArrayMatcher","3":{"1":"goog.ui.ac.ArrayMatcher.html"}},"2":4},"23":"goog.ui.ac.ArrayMatcher.html","24":"goog.ui.ac.ArrayMatcher"}]}}