{"2":{"1":[{"1":"goog.date.Interval","5":{"1":"closure/goog/date/date.js","2":482,"3":"https://github.com/google/closure-library/blob/master/closure/goog/date/date.js#L482"},"7":{"1":[{"2":"<p>Class representing a date/time interval. Used for date calculations.</p>\n <pre>\n new goog.date.Interval(0, 1) // One month\n new goog.date.Interval(0, 0, 3, 1) // Three days and one hour\n new goog.date.Interval(goog.date.Interval.DAYS, 1) // One day\n </pre>\n"}]},"8":{"4":true,"7":true},"12":[{"1":{"1":"Interval.fromIsoString","2":{"1":"closure/goog/date/date.js","2":513,"3":"https://github.com/google/closure-library/blob/master/closure/goog/date/date.js#L513"},"3":{"1":[{"2":"<p>Parses an XML Schema duration (ISO 8601 extended).</p>\n"}]},"10":[{"1":[{"2":"<p><a href=\"http://www.w3.org/TR/xmlschema-2/#duration\">http://www.w3.org/TR/xmlschema-2/#duration</a></p>\n"}]}]},"4":[{"1":"duration","2":{"4":{"1":"string","4":true}},"3":{"1":[{"2":"<p>An XML schema duration in textual format.\nRecurring durations and weeks are not supported.</p>\n"}]}}],"5":{"2":{"6":{"1":[{"4":{"1":"goog.date.Interval","3":{"1":"goog.date.Interval.html"}}},{"10":true}]}},"3":{"1":[{"2":"<p>The duration as a goog.date.Interval or null\nif the parse fails.</p>\n"}]}}}],"13":[{"1":{"1":"Interval.DAYS","2":{"1":"closure/goog/date/date.js","2":643,"3":"https://github.com/google/closure-library/blob/master/closure/goog/date/date.js#L643"},"3":{"1":[{"2":"<p>Days constant for the date parts.</p>\n"}]}},"2":{"4":{"1":"string","4":true}}},{"1":{"1":"Interval.HOURS","2":{"1":"closure/goog/date/date.js","2":650,"3":"https://github.com/google/closure-library/blob/master/closure/goog/date/date.js#L650"},"3":{"1":[{"2":"<p>Hours constant for the date parts.</p>\n"}]}},"2":{"4":{"1":"string","4":true}}},{"1":{"1":"Interval.MINUTES","2":{"1":"closure/goog/date/date.js","2":657,"3":"https://github.com/google/closure-library/blob/master/closure/goog/date/date.js#L657"},"3":{"1":[{"2":"<p>Minutes constant for the date parts.</p>\n"}]}},"2":{"4":{"1":"string","4":true}}},{"1":{"1":"Interval.MONTHS","2":{"1":"closure/goog/date/date.js","2":636,"3":"https://github.com/google/closure-library/blob/master/closure/goog/date/date.js#L636"},"3":{"1":[{"2":"<p>Months constant for the date parts.</p>\n"}]}},"2":{"4":{"1":"string","4":true}}},{"1":{"1":"Interval.SECONDS","2":{"1":"closure/goog/date/date.js","2":664,"3":"https://github.com/google/closure-library/blob/master/closure/goog/date/date.js#L664"},"3":{"1":[{"2":"<p>Seconds constant for the date parts.</p>\n"}]}},"2":{"4":{"1":"string","4":true}}},{"1":{"1":"Interval.YEARS","2":{"1":"closure/goog/date/date.js","2":629,"3":"https://github.com/google/closure-library/blob/master/closure/goog/date/date.js#L629"},"3":{"1":[{"2":"<p>Years constant for the date parts.</p>\n"}]}},"2":{"4":{"1":"string","4":true}}}],"14":{"1":{"1":"Interval","2":{"1":"closure/goog/date/date.js","2":482,"3":"https://github.com/google/closure-library/blob/master/closure/goog/date/date.js#L482"},"3":{"1":[{"2":"<p>Class representing a date/time interval. Used for date calculations.</p>\n <pre>\n new goog.date.Interval(0, 1) // One month\n new goog.date.Interval(0, 0, 3, 1) // Three days and one hour\n new goog.date.Interval(goog.date.Interval.DAYS, 1) // One day\n </pre>\n"}]}},"3":true,"4":[{"1":"opt_years","2":{"1":true,"6":{"1":[{"4":{"1":"number","4":true}},{"4":{"1":"string","4":true}},{"9":true}]}},"3":{"1":[{"2":"<p>Years or string representing date part.</p>\n"}]}},{"1":"opt_months","2":{"1":true,"6":{"1":[{"4":{"1":"number","4":true}},{"9":true}]}},"3":{"1":[{"2":"<p>Months or number of whatever date part specified\nby first parameter.</p>\n"}]}},{"1":"opt_days","2":{"1":true,"6":{"1":[{"4":{"1":"number","4":true}},{"9":true}]}},"3":{"1":[{"2":"<p>Days.</p>\n"}]}},{"1":"opt_hours","2":{"1":true,"6":{"1":[{"4":{"1":"number","4":true}},{"9":true}]}},"3":{"1":[{"2":"<p>Hours.</p>\n"}]}},{"1":"opt_minutes","2":{"1":true,"6":{"1":[{"4":{"1":"number","4":true}},{"9":true}]}},"3":{"1":[{"2":"<p>Minutes.</p>\n"}]}},{"1":"opt_seconds","2":{"1":true,"6":{"1":[{"4":{"1":"number","4":true}},{"9":true}]}},"3":{"1":[{"2":"<p>Seconds.</p>\n"}]}}]},"15":[{"1":{"1":"add","2":{"1":"closure/goog/date/date.js","2":713,"3":"https://github.com/google/closure-library/blob/master/closure/goog/date/date.js#L713"},"3":{"1":[{"2":"<p>Adds the Interval in the argument to this Interval field by field.</p>\n"}]}},"4":[{"1":"interval","2":{"6":{"1":[{"4":{"1":"goog.date.Interval","3":{"1":"goog.date.Interval.html"}}},{"10":true}]}},"3":{"1":[{"2":"<p>The Interval to add.</p>\n"}]}}]},{"1":{"1":"clone","2":{"1":"closure/goog/date/date.js","2":618,"3":"https://github.com/google/closure-library/blob/master/closure/goog/date/date.js#L618"},"3":{}},"5":{"2":{"4":{"1":"goog.date.Interval","3":{"1":"goog.date.Interval.html"}}},"3":{"1":[{"2":"<p>A clone of the interval object.</p>\n"}]}}},{"1":{"1":"equals","2":{"1":"closure/goog/date/date.js","2":608,"3":"https://github.com/google/closure-library/blob/master/closure/goog/date/date.js#L608"},"3":{"1":[{"2":"<p>Tests whether the given interval is equal to this interval.\nNote, this is a simple field-by-field comparison, it doesn&#39;t\naccount for comparisons like &#34;12 months &#61;&#61; 1 year&#34;.</p>\n"}]}},"4":[{"1":"other","2":{"6":{"1":[{"4":{"1":"goog.date.Interval","3":{"1":"goog.date.Interval.html"}}},{"10":true}]}},"3":{"1":[{"2":"<p>The interval to test.</p>\n"}]}}],"5":{"2":{"4":{"1":"boolean","4":true}},"3":{"1":[{"2":"<p>Whether the intervals are equal.</p>\n"}]}}},{"1":{"1":"getInverse","2":{"1":"closure/goog/date/date.js","2":679,"3":"https://github.com/google/closure-library/blob/master/closure/goog/date/date.js#L679"},"3":{}},"5":{"2":{"4":{"1":"goog.date.Interval","3":{"1":"goog.date.Interval.html"}}},"3":{"1":[{"2":"<p>Negative of this interval.</p>\n"}]}}},{"1":{"1":"getTotalSeconds","2":{"1":"closure/goog/date/date.js","2":701,"3":"https://github.com/google/closure-library/blob/master/closure/goog/date/date.js#L701"},"3":{"1":[{"2":"<p>Gets the total number of seconds in the time interval. Assumes that months\nand years are empty.</p>\n"}]}},"5":{"2":{"4":{"1":"number","4":true}},"3":{"1":[{"2":"<p>Total number of seconds in the interval.</p>\n"}]}}},{"1":{"1":"isZero","2":{"1":"closure/goog/date/date.js","2":670,"3":"https://github.com/google/closure-library/blob/master/closure/goog/date/date.js#L670"},"3":{}},"5":{"2":{"4":{"1":"boolean","4":true}},"3":{"1":[{"2":"<p>Whether all fields of the interval are zero.</p>\n"}]}}},{"1":{"1":"times","2":{"1":"closure/goog/date/date.js","2":689,"3":"https://github.com/google/closure-library/blob/master/closure/goog/date/date.js#L689"},"3":{"1":[{"2":"<p>Calculates n * (this interval) by memberwise multiplication.</p>\n"}]}},"4":[{"1":"n","2":{"4":{"1":"number","4":true}},"3":{"1":[{"2":"<p>An integer.</p>\n"}]}}],"5":{"2":{"4":{"1":"goog.date.Interval","3":{"1":"goog.date.Interval.html"}}},"3":{"1":[{"2":"<p>n * this.</p>\n"}]}}},{"1":{"1":"toIsoString","2":{"1":"closure/goog/date/date.js","2":547,"3":"https://github.com/google/closure-library/blob/master/closure/goog/date/date.js#L547"},"3":{"1":[{"2":"<p>Serializes goog.date.Interval into XML Schema duration (ISO 8601 extended).</p>\n"}]},"10":[{"1":[{"2":"<p><a href=\"http://www.w3.org/TR/xmlschema-2/#duration\">http://www.w3.org/TR/xmlschema-2/#duration</a></p>\n"}]}]},"4":[{"1":"opt_verbose","2":{"1":true,"6":{"1":[{"4":{"1":"boolean","4":true}},{"9":true}]}},"3":{"1":[{"2":"<p>Include zero fields in the duration string.</p>\n"}]}}],"5":{"2":{"6":{"1":[{"4":{"1":"string","4":true}},{"10":true}]}},"3":{"1":[{"2":"<p>An XML schema duration in ISO 8601 extended format,\nor null if the interval contains both positive and negative fields.</p>\n"}]}}}],"16":[{"1":{"1":"days","2":{"1":"closure/goog/date/date.js","2":716,"3":"https://github.com/google/closure-library/blob/master/closure/goog/date/date.js#L716"},"3":{}},"2":{"4":{"1":"number","4":true}}},{"1":{"1":"hours","2":{"1":"closure/goog/date/date.js","2":717,"3":"https://github.com/google/closure-library/blob/master/closure/goog/date/date.js#L717"},"3":{}},"2":{"4":{"1":"number","4":true}}},{"1":{"1":"minutes","2":{"1":"closure/goog/date/date.js","2":718,"3":"https://github.com/google/closure-library/blob/master/closure/goog/date/date.js#L718"},"3":{}},"2":{"4":{"1":"number","4":true}}},{"1":{"1":"months","2":{"1":"closure/goog/date/date.js","2":715,"3":"https://github.com/google/closure-library/blob/master/closure/goog/date/date.js#L715"},"3":{}},"2":{"4":{"1":"number","4":true}}},{"1":{"1":"seconds","2":{"1":"closure/goog/date/date.js","2":719,"3":"https://github.com/google/closure-library/blob/master/closure/goog/date/date.js#L719"},"3":{}},"2":{"4":{"1":"number","4":true}}},{"1":{"1":"years","2":{"1":"closure/goog/date/date.js","2":714,"3":"https://github.com/google/closure-library/blob/master/closure/goog/date/date.js#L714"},"3":{}},"2":{"4":{"1":"number","4":true}}}],"21":{"1":{"1":"goog.date.Interval","3":{"1":"goog.date.Interval.html"}},"2":4},"23":"goog.date.Interval.html","24":"goog.date.Interval"}]}}