{"2":{"1":[{"1":"goog.soy","5":{"1":"closure/goog/soy/data.js","2":24,"3":"https://github.com/google/closure-library/blob/master/closure/goog/soy/data.js#L24"},"6":{"1":[{"1":"Renderer","2":"goog.soy.Renderer.html","3":{"1":[{"2":"<p>Creates a new soy renderer.</p>\n"}]}}],"3":[{"1":"InjectedDataSupplier","2":"goog.soy.InjectedDataSupplier.html","3":{"1":[{"2":"<p>An interface for a supplier that provides Soy injected data.</p>\n"}]},"4":{"5":true}}]},"7":{},"8":{},"10":[{"1":{"1":"StrictTemplate","2":{"1":"closure/goog/soy/soy.js","2":50,"3":"https://github.com/google/closure-library/blob/master/closure/goog/soy/soy.js#L50"},"3":{"1":[{"2":"<p>Type definition for strict Soy templates. Very useful when passing a template\nas an argument.</p>\n"}]}},"2":{"3":{"3":[{"8":true},{"1":true,"10":true},{"1":true,"6":{}}],"4":{"4":{"1":"goog.soy.data.SanitizedContent","3":{"1":"goog.soy.data.SanitizedContent.html"}}}}}}],"12":[{"1":{"1":"convertToElement","2":{"1":"closure/goog/soy/soy.js","2":165,"3":"https://github.com/google/closure-library/blob/master/closure/goog/soy/soy.js#L165"},"3":{"1":[{"2":"<p>Converts a processed Soy template into a single node. If the rendered\nHTML string represents a single node, then that node is returned. Otherwise,\na DIV element is returned containing the rendered nodes.</p>\n"}]}},"4":[{"1":"templateResult","2":{"4":{"1":"goog.soy.data.SanitizedContent","3":{"1":"goog.soy.data.SanitizedContent.html"}}},"3":{"1":[{"2":"<p>The processed\ntemplate of kind HTML or TEXT (which will be escaped).</p>\n"}]}},{"1":"opt_domHelper","2":{"1":true,"6":{"1":[{"4":{"1":"goog.dom.DomHelper","3":{"1":"goog.dom.DomHelper.html"}}},{"10":true},{"9":true}]}},"3":{"1":[{"2":"<p>The DOM helper used to\ncreate DOM nodes; defaults to <code>goog.dom.getDomHelper</code>.</p>\n"}]}}],"5":{"2":{"4":{"1":"Element"}},"3":{"1":[{"2":"<p>Rendered template contents, wrapped in a parent DIV\nelement if necessary.</p>\n"}]}}},{"1":{"1":"renderAsElement","2":{"1":"closure/goog/soy/soy.js","2":141,"3":"https://github.com/google/closure-library/blob/master/closure/goog/soy/soy.js#L141"},"3":{"1":[{"2":"<p>Renders a Soy template into a single node. If the rendered\nHTML string represents a single node, then that node is returned. Otherwise,\na DIV element is returned containing the rendered nodes.</p>\n"}]}},"2":["ARG_TYPES"],"4":[{"1":"template","2":{"6":{"1":[{"3":{"3":[{"6":{"1":[{"4":{"1":"ARG_TYPES"}},{"10":true}]}},{"1":true,"10":true},{"1":true,"6":{}}],"4":{"7":true}}},{"10":true}]}},"3":{"1":[{"2":"<p>The Soy template defining the element&#39;s content.</p>\n"}]}},{"1":"opt_templateData","2":{"1":true,"6":{"1":[{"4":{"1":"ARG_TYPES"}},{"10":true},{"9":true}]}},"3":{"1":[{"2":"<p>The data for the template.</p>\n"}]}},{"1":"opt_injectedData","2":{"1":true,"6":{"1":[{"4":{"1":"Object","4":true}},{"10":true},{"9":true}]}},"3":{"1":[{"2":"<p>The injected data for the template.</p>\n"}]}},{"1":"opt_domHelper","2":{"1":true,"6":{"1":[{"4":{"1":"goog.dom.DomHelper","3":{"1":"goog.dom.DomHelper.html"}}},{"10":true},{"9":true}]}},"3":{"1":[{"2":"<p>The DOM helper used to\ncreate DOM nodes; defaults to <code>goog.dom.getDomHelper</code>.</p>\n"}]}}],"5":{"2":{"4":{"1":"Element"}},"3":{"1":[{"2":"<p>Rendered template contents, wrapped in a parent DIV\nelement if necessary.</p>\n"}]}}},{"1":{"1":"renderAsFragment","2":{"1":"closure/goog/soy/soy.js","2":109,"3":"https://github.com/google/closure-library/blob/master/closure/goog/soy/soy.js#L109"},"3":{"1":[{"2":"<p>Renders a Soy template into a single node or a document\nfragment. If the rendered HTML string represents a single node, then that\nnode is returned (note that this is <em>not</em> a fragment, despite them name of\nthe method). Otherwise a document fragment is returned containing the\nrendered nodes.</p>\n"}]}},"2":["ARG_TYPES"],"4":[{"1":"template","2":{"6":{"1":[{"3":{"3":[{"6":{"1":[{"4":{"1":"ARG_TYPES"}},{"10":true}]}},{"1":true,"10":true},{"1":true,"6":{}}],"4":{"7":true}}},{"10":true}]}},"3":{"1":[{"2":"<p>The Soy template defining the element&#39;s content.</p>\n"}]}},{"1":"opt_templateData","2":{"1":true,"6":{"1":[{"4":{"1":"ARG_TYPES"}},{"10":true},{"9":true}]}},"3":{"1":[{"2":"<p>The data for the template.</p>\n"}]}},{"1":"opt_injectedData","2":{"1":true,"6":{"1":[{"4":{"1":"Object","4":true}},{"10":true},{"9":true}]}},"3":{"1":[{"2":"<p>The injected data for the template.</p>\n"}]}},{"1":"opt_domHelper","2":{"1":true,"6":{"1":[{"4":{"1":"goog.dom.DomHelper","3":{"1":"goog.dom.DomHelper.html"}}},{"10":true},{"9":true}]}},"3":{"1":[{"2":"<p>The DOM helper used to\ncreate DOM nodes; defaults to <code>goog.dom.getDomHelper</code>.</p>\n"}]}}],"5":{"2":{"4":{"1":"Node"}},"3":{"1":[{"2":"<p>The resulting node or document fragment.</p>\n"}]}}},{"1":{"1":"renderElement","2":{"1":"closure/goog/soy/soy.js","2":82,"3":"https://github.com/google/closure-library/blob/master/closure/goog/soy/soy.js#L82"},"3":{"1":[{"2":"<p>Renders a Soy template and then set the output string as\nthe innerHTML of an element. It is recommended to use this helper function\ninstead of directly setting innerHTML in your hand-written code, so that it\nwill be easier to audit the code for cross-site scripting vulnerabilities.</p>\n"}]}},"2":["ARG_TYPES"],"4":[{"1":"element","2":{"6":{"1":[{"4":{"1":"Element"}},{"10":true}]}},"3":{"1":[{"2":"<p>The element whose content we are rendering into.</p>\n"}]}},{"1":"template","2":{"6":{"1":[{"3":{"3":[{"6":{"1":[{"4":{"1":"ARG_TYPES"}},{"10":true}]}},{"1":true,"10":true},{"1":true,"6":{}}],"4":{"7":true}}},{"10":true}]}},"3":{"1":[{"2":"<p>The Soy template defining the element&#39;s content.</p>\n"}]}},{"1":"opt_templateData","2":{"1":true,"6":{"1":[{"4":{"1":"ARG_TYPES"}},{"10":true},{"9":true}]}},"3":{"1":[{"2":"<p>The data for the template.</p>\n"}]}},{"1":"opt_injectedData","2":{"1":true,"6":{"1":[{"4":{"1":"Object","4":true}},{"10":true},{"9":true}]}},"3":{"1":[{"2":"<p>The injected data for the template.</p>\n"}]}}]},{"1":{"1":"renderHtml","2":{"1":"closure/goog/soy/soy.js","2":64,"3":"https://github.com/google/closure-library/blob/master/closure/goog/soy/soy.js#L64"},"3":{"1":[{"2":"<p>Sets the processed template as the innerHTML of an element. It is recommended\nto use this helper function instead of directly setting innerHTML in your\nhand-written code, so that it will be easier to audit the code for cross-site\nscripting vulnerabilities.</p>\n"}]}},"2":["ARG_TYPES"],"4":[{"1":"element","2":{"6":{"1":[{"4":{"1":"Element"}},{"10":true}]}},"3":{"1":[{"2":"<p>The element whose content we are rendering into.</p>\n"}]}},{"1":"templateResult","2":{"4":{"1":"goog.soy.data.SanitizedContent","3":{"1":"goog.soy.data.SanitizedContent.html"}}},"3":{"1":[{"2":"<p>The processed\ntemplate of kind HTML or TEXT (which will be escaped).</p>\n"}]}}]}],"20":[{"1":{"1":"goog.soy.REQUIRE_STRICT_AUTOESCAPE","2":{"1":"closure/goog/soy/soy.js","2":41,"3":"https://github.com/google/closure-library/blob/master/closure/goog/soy/soy.js#L41"},"3":{"1":[{"2":"<p>Whether to require all Soy templates to be &#34;strict html&#34;.\nSoy templates that use strict autoescaping forbid noAutoescape along with\nmany dangerous directives, and return a runtime type SanitizedContent that\nmarks them as safe.</p>\n<p>If this flag is enabled, Soy templates will fail to render if a template\nreturns plain text -- indicating it is a non-strict template.</p>\n"}]},"6":{"1":true}},"2":{"4":{"1":"boolean","4":true}}}],"21":{"1":{"1":"goog.soy","3":{"1":"goog.soy.html"}},"2":4},"23":"goog.soy.html","24":"goog.soy"}]}}