{"2":{"1":[{"1":"goog.net.XmlHttp.ReadyState","5":{"1":"closure/goog/net/xmlhttp.js","2":98,"3":"https://github.com/google/closure-library/blob/master/closure/goog/net/xmlhttp.js#L98"},"7":{"1":[{"2":"<p>Status constants for XMLHTTP, matches:\nhttps://msdn.microsoft.com/en-us/library/ms534361(v&#61;vs.85).aspx</p>\n"}]},"8":{},"11":{"1":{"4":{"1":"number","3":{"1":"https://developer.mozilla.org/en-US/docs/Web/JavaScript/Reference/Global_Objects/Number"},"4":true}},"2":[{"1":"COMPLETE","2":{"1":[{"2":"<p>Constant for when xmlhttprequest.readyState is completed</p>\n"}]}},{"1":"INTERACTIVE","2":{"1":[{"2":"<p>Constant for when xmlhttprequest.readyState is in an interactive state.</p>\n"}]}},{"1":"LOADED","2":{"1":[{"2":"<p>Constant for when xmlhttprequest.readyState is loaded.</p>\n"}]}},{"1":"LOADING","2":{"1":[{"2":"<p>Constant for when xmlhttprequest.readyState is loading.</p>\n"}]}},{"1":"UNINITIALIZED","2":{"1":[{"2":"<p>Constant for when xmlhttprequest.readyState is uninitialized</p>\n"}]}}]},"21":{"1":{"1":"goog.net.XmlHttp","3":{"1":"goog.net.XmlHttp.html"}}},"23":"goog.net.XmlHttp.ReadyState.html","24":"goog.net.XmlHttp.ReadyState"}]}}