{"2":{"1":[{"1":"goog.ui.Dialog.DefaultButtonCaptions","5":{"1":"closure/goog/ui/dialog.js","2":1497,"3":"https://github.com/google/closure-library/blob/master/closure/goog/ui/dialog.js#L1497"},"7":{"1":[{"2":"<p>The default captions for the default buttons.</p>\n"}]},"8":{},"11":{"1":{"4":{"1":"string","4":true}},"2":[{"1":"CANCEL"},{"1":"CONTINUE"},{"1":"NO"},{"1":"OK"},{"1":"SAVE"},{"1":"YES"}]},"21":{"1":{"1":"goog.ui.Dialog.DefaultButtonCaptions","3":{"1":"goog.ui.Dialog.DefaultButtonCaptions.html"}},"2":4},"23":"goog.ui.Dialog.DefaultButtonCaptions.html","24":"goog.ui.Dialog.DefaultButtonCaptions"}]}}