{"2":{"1":[{"1":"goog.events.KeyCodes","5":{"1":"closure/goog/events/keycodes.js","2":37,"3":"https://github.com/google/closure-library/blob/master/closure/goog/events/keycodes.js#L37"},"7":{"1":[{"2":"<p>Key codes for common characters.</p>\n<p>This list is not localized and therefore some of the key codes are not\ncorrect for non US keyboard layouts. See comments below.</p>\n"}]},"8":{},"11":{"1":{"4":{"1":"number","4":true}},"2":[{"1":"A"},{"1":"ALT"},{"1":"APOSTROPHE"},{"1":"AT_SIGN"},{"1":"B"},{"1":"BACKSLASH"},{"1":"BACKSPACE"},{"1":"C"},{"1":"CAPS_LOCK"},{"1":"CLOSE_SQUARE_BRACKET"},{"1":"COMMA"},{"1":"CONTEXT_MENU"},{"1":"CTRL"},{"1":"D"},{"1":"DASH"},{"1":"DELETE"},{"1":"DOWN"},{"1":"E"},{"1":"EIGHT"},{"1":"END"},{"1":"ENTER"},{"1":"EQUALS"},{"1":"ESC"},{"1":"F"},{"1":"F1"},{"1":"F10"},{"1":"F11"},{"1":"F12"},{"1":"F2"},{"1":"F3"},{"1":"F4"},{"1":"F5"},{"1":"F6"},{"1":"F7"},{"1":"F8"},{"1":"F9"},{"1":"FF_DASH"},{"1":"FF_EQUALS"},{"1":"FF_SEMICOLON"},{"1":"FIRST_MEDIA_KEY"},{"1":"FIVE"},{"1":"FOUR"},{"1":"G"},{"1":"H"},{"1":"HOME"},{"1":"I"},{"1":"INSERT"},{"1":"J"},{"1":"K"},{"1":"L"},{"1":"LAST_MEDIA_KEY"},{"1":"LEFT"},{"1":"M"},{"1":"MAC_ENTER"},{"1":"MAC_FF_META"},{"1":"MAC_WK_CMD_LEFT"},{"1":"MAC_WK_CMD_RIGHT"},{"1":"META"},{"1":"N"},{"1":"NINE"},{"1":"NUMLOCK"},{"1":"NUM_CENTER"},{"1":"NUM_DIVISION"},{"1":"NUM_EIGHT"},{"1":"NUM_FIVE"},{"1":"NUM_FOUR"},{"1":"NUM_MINUS"},{"1":"NUM_MULTIPLY"},{"1":"NUM_NINE"},{"1":"NUM_ONE"},{"1":"NUM_PERIOD"},{"1":"NUM_PLUS"},{"1":"NUM_SEVEN"},{"1":"NUM_SIX"},{"1":"NUM_THREE"},{"1":"NUM_TWO"},{"1":"NUM_ZERO"},{"1":"O"},{"1":"ONE"},{"1":"OPEN_SQUARE_BRACKET"},{"1":"P"},{"1":"PAGE_DOWN"},{"1":"PAGE_UP"},{"1":"PAUSE"},{"1":"PERIOD"},{"1":"PHANTOM"},{"1":"PLUS_SIGN"},{"1":"PRINT_SCREEN"},{"1":"Q"},{"1":"QUESTION_MARK"},{"1":"R"},{"1":"RIGHT"},{"1":"S"},{"1":"SCROLL_LOCK"},{"1":"SEMICOLON"},{"1":"SEVEN"},{"1":"SHIFT"},{"1":"SINGLE_QUOTE"},{"1":"SIX"},{"1":"SLASH"},{"1":"SPACE"},{"1":"T"},{"1":"TAB"},{"1":"THREE"},{"1":"TILDE"},{"1":"TWO"},{"1":"U"},{"1":"UP"},{"1":"V"},{"1":"VK_NONAME"},{"1":"W"},{"1":"WIN_IME"},{"1":"WIN_KEY"},{"1":"WIN_KEY_FF_LINUX"},{"1":"WIN_KEY_RIGHT"},{"1":"X"},{"1":"Y"},{"1":"Z"},{"1":"ZERO"}]},"12":[{"1":{"1":"KeyCodes.firesKeyPressEvent","2":{"1":"closure/goog/events/keycodes.js","2":261,"3":"https://github.com/google/closure-library/blob/master/closure/goog/events/keycodes.js#L261"},"3":{"1":[{"2":"<p>Returns true if the key fires a keypress event in the current browser.</p>\n<p>Accoridng to MSDN [1] IE only fires keypress events for the following keys:</p>\n<ul><li>Letters: A - Z (uppercase and lowercase)</li><li>Numerals: 0 - 9</li><li>Symbols: ! &#64; # $ % ^ &amp; * ( ) _ - &#43; &#61; &lt; [ ] { } , . / ? \\ | &#39; &#96; &#34; ~</li><li>System: ESC, SPACEBAR, ENTER</li></ul>\n<p>That&#39;s not entirely correct though, for instance there&#39;s no distinction\nbetween upper and lower case letters.</p>\n<p>[1] http://msdn2.microsoft.com/en-us/library/ms536939(VS.85).aspx)</p>\n<p>Safari is similar to IE, but does not fire keypress for ESC.</p>\n<p>Additionally, IE6 does not fire keydown or keypress events for letters when\nthe control or alt keys are held down and the shift key is not. IE7 does\nfire keydown in these cases, though, but not keypress.</p>\n"}]}},"4":[{"1":"keyCode","2":{"4":{"1":"number","4":true}},"3":{"1":[{"2":"<p>A key code.</p>\n"}]}},{"1":"opt_heldKeyCode","2":{"1":true,"6":{"1":[{"4":{"1":"number","4":true}},{"9":true}]}},"3":{"1":[{"2":"<p>Key code of a currently-held key.</p>\n"}]}},{"1":"opt_shiftKey","2":{"1":true,"6":{"1":[{"4":{"1":"boolean","4":true}},{"9":true}]}},"3":{"1":[{"2":"<p>Whether the shift key is held down.</p>\n"}]}},{"1":"opt_ctrlKey","2":{"1":true,"6":{"1":[{"4":{"1":"boolean","4":true}},{"9":true}]}},"3":{"1":[{"2":"<p>Whether the control key is held down.</p>\n"}]}},{"1":"opt_altKey","2":{"1":true,"6":{"1":[{"4":{"1":"boolean","4":true}},{"9":true}]}},"3":{"1":[{"2":"<p>Whether the alt key is held down.</p>\n"}]}},{"1":"opt_metaKey","2":{"1":true,"6":{"1":[{"4":{"1":"boolean","4":true}},{"9":true}]}},"3":{"1":[{"2":"<p>Whether the meta key is held down.</p>\n"}]}}],"5":{"2":{"4":{"1":"boolean","4":true}},"3":{"1":[{"2":"<p>Whether it&#39;s a key that fires a keypress event.</p>\n"}]}}},{"1":{"1":"KeyCodes.isCharacterKey","2":{"1":"closure/goog/events/keycodes.js","2":339,"3":"https://github.com/google/closure-library/blob/master/closure/goog/events/keycodes.js#L339"},"3":{"1":[{"2":"<p>Returns true if the key produces a character.\nThis does not cover characters on non-US keyboards (Russian, Hebrew, etc.).</p>\n"}]}},"4":[{"1":"keyCode","2":{"4":{"1":"number","4":true}},"3":{"1":[{"2":"<p>A key code.</p>\n"}]}}],"5":{"2":{"4":{"1":"boolean","4":true}},"3":{"1":[{"2":"<p>Whether it&#39;s a character key.</p>\n"}]}}},{"1":{"1":"KeyCodes.isTextModifyingKeyEvent","2":{"1":"closure/goog/events/keycodes.js","2":186,"3":"https://github.com/google/closure-library/blob/master/closure/goog/events/keycodes.js#L186"},"3":{"1":[{"2":"<p>Returns false if the event does not contain a text modifying key.</p>\n<p>When it returns true, the event might be text modifying. It is infeasible to\nsay for sure because of the many different keyboard layouts, so this method\nerrs on the side of assuming a key event is text-modifiable if we cannot be\ncertain it is not. As an example, it will return true for ctrl&#43;a, though in\nmany standard keyboard layouts that key combination would mean &#34;select all&#34;,\nand not actually modify the text.</p>\n"}]}},"4":[{"1":"e","2":{"6":{"1":[{"4":{"1":"goog.events.BrowserEvent","3":{"1":"goog.events.BrowserEvent.html"}}},{"10":true}]}},"3":{"1":[{"2":"<p>A key event.</p>\n"}]}}],"5":{"2":{"4":{"1":"boolean","4":true}},"3":{"1":[{"2":"<p>Whether it&#39;s a text modifying key.</p>\n"}]}}},{"1":{"1":"KeyCodes.normalizeGeckoKeyCode","2":{"1":"closure/goog/events/keycodes.js","2":409,"3":"https://github.com/google/closure-library/blob/master/closure/goog/events/keycodes.js#L409"},"3":{"1":[{"2":"<p>Normalizes key codes from their Gecko-specific value to the general one.</p>\n"}]}},"4":[{"1":"keyCode","2":{"4":{"1":"number","4":true}},"3":{"1":[{"2":"<p>The native key code.</p>\n"}]}}],"5":{"2":{"4":{"1":"number","4":true}},"3":{"1":[{"2":"<p>The normalized key code.</p>\n"}]}}},{"1":{"1":"KeyCodes.normalizeKeyCode","2":{"1":"closure/goog/events/keycodes.js","2":393,"3":"https://github.com/google/closure-library/blob/master/closure/goog/events/keycodes.js#L393"},"3":{"1":[{"2":"<p>Normalizes key codes from OS/Browser-specific value to the general one.</p>\n"}]}},"4":[{"1":"keyCode","2":{"4":{"1":"number","4":true}},"3":{"1":[{"2":"<p>The native key code.</p>\n"}]}}],"5":{"2":{"4":{"1":"number","4":true}},"3":{"1":[{"2":"<p>The normalized key code.</p>\n"}]}}},{"1":{"1":"KeyCodes.normalizeMacWebKitKeyCode","2":{"1":"closure/goog/events/keycodes.js","2":432,"3":"https://github.com/google/closure-library/blob/master/closure/goog/events/keycodes.js#L432"},"3":{"1":[{"2":"<p>Normalizes key codes from their Mac WebKit-specific value to the general one.</p>\n"}]}},"4":[{"1":"keyCode","2":{"4":{"1":"number","4":true}},"3":{"1":[{"2":"<p>The native key code.</p>\n"}]}}],"5":{"2":{"4":{"1":"number","4":true}},"3":{"1":[{"2":"<p>The normalized key code.</p>\n"}]}}}],"21":{"1":{"1":"goog.events.KeyCodes","3":{"1":"goog.events.KeyCodes.html"}},"2":4},"23":"goog.events.KeyCodes.html","24":"goog.events.KeyCodes"}]}}