{"2":{"1":[{"1":"goog.dom.browserrange.Error","5":{"1":"closure/goog/dom/browserrange/browserrange.js","2":43,"3":"https://github.com/google/closure-library/blob/master/closure/goog/dom/browserrange/browserrange.js#L43"},"7":{"1":[{"2":"<p>Common error constants.</p>\n"}]},"8":{},"11":{"1":{"4":{"1":"string","4":true}},"2":[{"1":"NOT_IMPLEMENTED"}]},"21":{"1":{"1":"goog.dom.browserrange.Error","3":{"1":"goog.dom.browserrange.Error.html"}},"2":4},"23":"goog.dom.browserrange.Error.html","24":"goog.dom.browserrange.Error"}]}}