{"2":{"1":[{"1":"goog.labs.dom.PageVisibilityState","5":{"1":"closure/goog/labs/dom/pagevisibilitymonitor.js","2":37,"3":"https://github.com/google/closure-library/blob/master/closure/goog/labs/dom/pagevisibilitymonitor.js#L37"},"7":{"1":[{"2":"<p>The different visibility states.</p>\n"}]},"8":{},"11":{"1":{"4":{"1":"string","4":true}},"2":[{"1":"HIDDEN"},{"1":"PRERENDER"},{"1":"UNLOADED"},{"1":"VISIBLE"}]},"21":{"1":{"1":"goog.labs.dom.PageVisibilityState","3":{"1":"goog.labs.dom.PageVisibilityState.html"}},"2":4},"23":"goog.labs.dom.PageVisibilityState.html","24":"goog.labs.dom.PageVisibilityState"}]}}