{"2":{"1":[{"1":"goog.proto","5":{"1":"closure/goog/proto/serializer.js","2":24,"3":"https://github.com/google/closure-library/blob/master/closure/goog/proto/serializer.js#L24"},"6":{"1":[{"1":"Serializer","2":"goog.proto.Serializer.html","3":{"1":[{"2":"<p>Object that can serialize objects or values to a protocol buffer string.</p>\n"}]}}]},"7":{},"8":{},"12":[{"1":{"1":"serialize","2":{"1":"closure/goog/proto/proto.js","2":39,"3":"https://github.com/google/closure-library/blob/master/closure/goog/proto/proto.js#L39"},"3":{"1":[{"2":"<p>Serializes an object or a value to a protocol buffer string.</p>\n"}]}},"4":[{"1":"object","2":{"6":{"1":[{"4":{"1":"Object","4":true}},{"10":true}]}},"3":{"1":[{"2":"<p>The object to serialize.</p>\n"}]}}],"5":{"2":{"4":{"1":"string","4":true}},"3":{"1":[{"2":"<p>The serialized protocol buffer string.</p>\n"}]}}}],"21":{"1":{"1":"goog.proto","3":{"1":"goog.proto.html"}},"2":4},"23":"goog.proto.html","24":"goog.proto"}]}}