{"2":{"1":[{"1":"goog.dom.safe.InsertAdjacentHtmlPosition","5":{"1":"closure/goog/dom/safe.js","2":55,"3":"https://github.com/google/closure-library/blob/master/closure/goog/dom/safe.js#L55"},"7":{},"8":{},"11":{"1":{"4":{"1":"string","4":true}},"2":[{"1":"AFTERBEGIN"},{"1":"AFTEREND"},{"1":"BEFOREBEGIN"},{"1":"BEFOREEND"}]},"21":{"1":{"1":"goog.dom.safe.InsertAdjacentHtmlPosition","3":{"1":"goog.dom.safe.InsertAdjacentHtmlPosition.html"}},"2":4},"23":"goog.dom.safe.InsertAdjacentHtmlPosition.html","24":"goog.dom.safe.InsertAdjacentHtmlPosition"}]}}